hafnia/__init__.py
hafnia/http.py
hafnia/log.py
hafnia/torch_helpers.py
hafnia/utils.py
hafnia/data/__init__.py
hafnia/data/factory.py
hafnia/dataset/dataset_details_uploader.py
hafnia/dataset/dataset_helpers.py
hafnia/dataset/dataset_names.py
hafnia/dataset/hafnia_dataset.py
hafnia/dataset/hafnia_dataset_types.py
hafnia/dataset/license_types.py
hafnia/dataset/dataset_recipe/dataset_recipe.py
hafnia/dataset/dataset_recipe/recipe_transforms.py
hafnia/dataset/dataset_recipe/recipe_types.py
hafnia/dataset/format_conversions/format_coco.py
hafnia/dataset/format_conversions/format_helpers.py
hafnia/dataset/format_conversions/format_image_classification_folder.py
hafnia/dataset/format_conversions/format_yolo.py
hafnia/dataset/format_conversions/torchvision_datasets.py
hafnia/dataset/operations/dataset_s3_storage.py
hafnia/dataset/operations/dataset_stats.py
hafnia/dataset/operations/dataset_transformations.py
hafnia/dataset/operations/table_transformations.py
hafnia/dataset/primitives/__init__.py
hafnia/dataset/primitives/bbox.py
hafnia/dataset/primitives/bitmask.py
hafnia/dataset/primitives/classification.py
hafnia/dataset/primitives/point.py
hafnia/dataset/primitives/polygon.py
hafnia/dataset/primitives/primitive.py
hafnia/dataset/primitives/segmentation.py
hafnia/dataset/primitives/utils.py
hafnia/experiment/__init__.py
hafnia/experiment/hafnia_logger.py
hafnia/platform/__init__.py
hafnia/platform/builder.py
hafnia/platform/dataset_recipe.py
hafnia/platform/datasets.py
hafnia/platform/download.py
hafnia/platform/experiment.py
hafnia/platform/s5cmd_utils.py
hafnia/platform/trainer_package.py
hafnia/visualizations/colors.py
hafnia/visualizations/image_visualizations.py
hafnia_cli/__init__.py
hafnia_cli/__main__.py
hafnia_cli/config.py
hafnia_cli/consts.py
hafnia_cli/dataset_cmds.py
hafnia_cli/dataset_recipe_cmds.py
hafnia_cli/experiment_cmds.py
hafnia_cli/keychain.py
hafnia_cli/profile_cmds.py
hafnia_cli/runc_cmds.py
hafnia_cli/trainer_package_cmds.py
hafnia-0.5.1.dist-info/METADATA
hafnia-0.5.1.dist-info/WHEEL
hafnia-0.5.1.dist-info/entry_points.txt
hafnia-0.5.1.dist-info/licenses/LICENSE
hafnia-0.5.1.dist-info/RECORD
