Metadata-Version: 2.4
Name: hafnia
Version: 0.5.1
Summary: Python SDK for communication with Hafnia platform.
Author-email: Milestone Systems <hafniaplatform@milestone.dk>
License-File: LICENSE
Requires-Python: >=3.10
Requires-Dist: boto3>=1.35.91
Requires-Dist: click>=8.1.8
Requires-Dist: emoji>=2.14.1
Requires-Dist: flatten-dict>=0.4.2
Requires-Dist: keyring>=25.6.0
Requires-Dist: mcp>=1.23.0
Requires-Dist: mlflow>=3.4.0
Requires-Dist: more-itertools>=10.7.0
Requires-Dist: opencv-python-headless>=4.11.0.86
Requires-Dist: pathspec>=0.12.1
Requires-Dist: pillow>=11.1.0
Requires-Dist: polars>=1.30.0
Requires-Dist: pyarrow>=18.1.0
Requires-Dist: pycocotools>=2.0.10
Requires-Dist: pydantic>=2.10.4
Requires-Dist: rich>=13.9.4
Requires-Dist: s5cmd>=0.2.0
Requires-Dist: sagemaker-mlflow>=0.1.0
Requires-Dist: seedir>=0.5.0
Requires-Dist: xxhash>=3.5.0
